<?xml version="1.0" encoding="UTF-8"?>
<GenRun Id="synth_1" LaunchPart="xc7a100tcsg324-1" LaunchTime="1743189472">
  <File Type="PA-TCL" Name="verifyInternalModule.tcl"/>
  <File Type="REPORTS-TCL" Name="verifyInternalModule_reports.tcl"/>
  <File Type="RDS-RDS" Name="verifyInternalModule.vds"/>
  <File Type="RDS-DCP" Name="verifyInternalModule.dcp"/>
  <File Type="RDS-UTIL-PB" Name="verifyInternalModule_utilization_synth.pb"/>
  <File Type="RDS-UTIL" Name="verifyInternalModule_utilization_synth.rpt"/>
  <FileSet Name="sources" Type="DesignSrcs" RelSrcDir="$PSRCDIR/sources_1">
    <Filter Type="Srcs"/>
    <File Path="$PSRCDIR/sources_1/new/PKDecode.sv">
      <FileInfo>
        <Attr Name="UsedIn" Val="synthesis"/>
        <Attr Name="UsedIn" Val="implementation"/>
        <Attr Name="UsedIn" Val="simulation"/>
      </FileInfo>
    </File>
    <File Path="$PSRCDIR/sources_1/new/SimpleBitUnpack.sv">
      <FileInfo>
        <Attr Name="UsedIn" Val="synthesis"/>
        <Attr Name="UsedIn" Val="implementation"/>
        <Attr Name="UsedIn" Val="simulation"/>
      </FileInfo>
    </File>
    <File Path="$PSRCDIR/sources_1/new/verifyInternalModule.sv">
      <FileInfo>
        <Attr Name="UsedIn" Val="synthesis"/>
        <Attr Name="UsedIn" Val="implementation"/>
        <Attr Name="UsedIn" Val="simulation"/>
      </FileInfo>
    </File>
    <File Path="$PSRCDIR/sources_1/new/Chi.sv">
      <FileInfo>
        <Attr Name="AutoDisabled" Val="1"/>
        <Attr Name="UsedIn" Val="synthesis"/>
        <Attr Name="UsedIn" Val="implementation"/>
        <Attr Name="UsedIn" Val="simulation"/>
      </FileInfo>
    </File>
    <File Path="$PSRCDIR/sources_1/new/Coefficient_three_bytes.sv">
      <FileInfo>
        <Attr Name="AutoDisabled" Val="1"/>
        <Attr Name="UsedIn" Val="synthesis"/>
        <Attr Name="UsedIn" Val="implementation"/>
        <Attr Name="UsedIn" Val="simulation"/>
      </FileInfo>
    </File>
    <File Path="$PSRCDIR/sources_1/new/Dilithium_pkg.sv">
      <FileInfo>
        <Attr Name="AutoDisabled" Val="1"/>
        <Attr Name="UsedIn" Val="synthesis"/>
        <Attr Name="UsedIn" Val="implementation"/>
        <Attr Name="UsedIn" Val="simulation"/>
      </FileInfo>
    </File>
    <File Path="$PSRCDIR/sources_1/new/ExpandA.sv">
      <FileInfo>
        <Attr Name="AutoDisabled" Val="1"/>
        <Attr Name="UsedIn" Val="synthesis"/>
        <Attr Name="UsedIn" Val="implementation"/>
        <Attr Name="UsedIn" Val="simulation"/>
      </FileInfo>
    </File>
    <File Path="$PSRCDIR/sources_1/new/Iota.sv">
      <FileInfo>
        <Attr Name="AutoDisabled" Val="1"/>
        <Attr Name="UsedIn" Val="synthesis"/>
        <Attr Name="UsedIn" Val="implementation"/>
        <Attr Name="UsedIn" Val="simulation"/>
      </FileInfo>
    </File>
    <File Path="$PSRCDIR/sources_1/new/Keccak.sv">
      <FileInfo>
        <Attr Name="AutoDisabled" Val="1"/>
        <Attr Name="UsedIn" Val="synthesis"/>
        <Attr Name="UsedIn" Val="implementation"/>
        <Attr Name="UsedIn" Val="simulation"/>
      </FileInfo>
    </File>
    <File Path="$PSRCDIR/sources_1/new/Pad10_1.sv">
      <FileInfo>
        <Attr Name="AutoDisabled" Val="1"/>
        <Attr Name="UsedIn" Val="synthesis"/>
        <Attr Name="UsedIn" Val="implementation"/>
        <Attr Name="UsedIn" Val="simulation"/>
      </FileInfo>
    </File>
    <File Path="$PSRCDIR/sources_1/new/Pi.sv">
      <FileInfo>
        <Attr Name="AutoDisabled" Val="1"/>
        <Attr Name="UsedIn" Val="synthesis"/>
        <Attr Name="UsedIn" Val="implementation"/>
        <Attr Name="UsedIn" Val="simulation"/>
      </FileInfo>
    </File>
    <File Path="$PSRCDIR/sources_1/new/RejNttPoly.sv">
      <FileInfo>
        <Attr Name="AutoDisabled" Val="1"/>
        <Attr Name="UsedIn" Val="synthesis"/>
        <Attr Name="UsedIn" Val="implementation"/>
        <Attr Name="UsedIn" Val="simulation"/>
      </FileInfo>
    </File>
    <File Path="$PSRCDIR/sources_1/new/Rho.sv">
      <FileInfo>
        <Attr Name="AutoDisabled" Val="1"/>
        <Attr Name="UsedIn" Val="synthesis"/>
        <Attr Name="UsedIn" Val="implementation"/>
        <Attr Name="UsedIn" Val="simulation"/>
      </FileInfo>
    </File>
    <File Path="$PSRCDIR/sources_1/new/Round.sv">
      <FileInfo>
        <Attr Name="AutoDisabled" Val="1"/>
        <Attr Name="UsedIn" Val="synthesis"/>
        <Attr Name="UsedIn" Val="implementation"/>
        <Attr Name="UsedIn" Val="simulation"/>
      </FileInfo>
    </File>
    <File Path="$PSRCDIR/sources_1/new/Shake.sv">
      <FileInfo>
        <Attr Name="AutoDisabled" Val="1"/>
        <Attr Name="UsedIn" Val="synthesis"/>
        <Attr Name="UsedIn" Val="implementation"/>
        <Attr Name="UsedIn" Val="simulation"/>
      </FileInfo>
    </File>
    <File Path="$PSRCDIR/sources_1/new/Theta.sv">
      <FileInfo>
        <Attr Name="AutoDisabled" Val="1"/>
        <Attr Name="UsedIn" Val="synthesis"/>
        <Attr Name="UsedIn" Val="implementation"/>
        <Attr Name="UsedIn" Val="simulation"/>
      </FileInfo>
    </File>
    <File Path="$PSRCDIR/sources_1/new/SignDecode.v">
      <FileInfo>
        <Attr Name="AutoDisabled" Val="1"/>
        <Attr Name="UsedIn" Val="synthesis"/>
        <Attr Name="UsedIn" Val="implementation"/>
        <Attr Name="UsedIn" Val="simulation"/>
      </FileInfo>
    </File>
    <File Path="$PSRCDIR/sources_1/new/CoefFromHalfByte.sv">
      <FileInfo>
        <Attr Name="AutoDisabled" Val="1"/>
        <Attr Name="UsedIn" Val="synthesis"/>
        <Attr Name="UsedIn" Val="implementation"/>
        <Attr Name="UsedIn" Val="simulation"/>
      </FileInfo>
    </File>
    <File Path="$PSRCDIR/sources_1/new/ExpandS.sv">
      <FileInfo>
        <Attr Name="AutoDisabled" Val="1"/>
        <Attr Name="UsedIn" Val="synthesis"/>
        <Attr Name="UsedIn" Val="implementation"/>
        <Attr Name="UsedIn" Val="simulation"/>
      </FileInfo>
    </File>
    <File Path="$PSRCDIR/sources_1/new/RejBoundedPoly.sv">
      <FileInfo>
        <Attr Name="AutoDisabled" Val="1"/>
        <Attr Name="UsedIn" Val="synthesis"/>
        <Attr Name="UsedIn" Val="implementation"/>
        <Attr Name="UsedIn" Val="simulation"/>
      </FileInfo>
    </File>
    <File Path="$PSRCDIR/sources_1/new/swapbits.sv">
      <FileInfo>
        <Attr Name="AutoDisabled" Val="1"/>
        <Attr Name="UsedIn" Val="synthesis"/>
        <Attr Name="UsedIn" Val="implementation"/>
        <Attr Name="UsedIn" Val="simulation"/>
      </FileInfo>
    </File>
    <File Path="$PSRCDIR/sources_1/new/key_internal.sv">
      <FileInfo>
        <Attr Name="UserDisabled" Val="1"/>
        <Attr Name="UsedIn" Val="synthesis"/>
        <Attr Name="UsedIn" Val="implementation"/>
        <Attr Name="UsedIn" Val="simulation"/>
      </FileInfo>
    </File>
    <Config>
      <Option Name="DesignMode" Val="RTL"/>
      <Option Name="TopModule" Val="verifyInternalModule"/>
      <Option Name="TopAutoSet" Val="TRUE"/>
    </Config>
  </FileSet>
  <FileSet Name="constrs_in" Type="Constrs" RelSrcDir="$PSRCDIR/constrs_1">
    <Filter Type="Constrs"/>
    <Config>
      <Option Name="ConstrsType" Val="XDC"/>
    </Config>
  </FileSet>
  <Strategy Version="1" Minor="2">
    <StratHandle Name="Vivado Synthesis Defaults" Flow="Vivado Synthesis 2018"/>
    <Step Id="synth_design"/>
  </Strategy>
</GenRun>
